vision_data_audit/__init__.py
vision_data_audit/cli.py
vision_data_audit/core.py
vision_data_audit-0.1.2.dist-info/WHEEL
vision_data_audit-0.1.2.dist-info/entry_points.txt
vision_data_audit-0.1.2.dist-info/METADATA
vision_data_audit-0.1.2.dist-info/RECORD
