Metadata-Version: 2.3
Name: vision-data-audit
Version: 0.1.2
Summary: Quick audit of an image folder: formats, sizes, mean/std, duplicates.
Author: Naif Ganadily
Author-email: Naif Ganadily <ganadilynaif@gmail.com>
Requires-Dist: numpy>=1.26,<2.4
Requires-Dist: pillow>=12.1.0
Requires-Python: >=3.10
